newmanga/__init__.py
newmanga/constants.py
newmanga/errors.py
newmanga/queries_data.py
newmanga/api/__init__.py
newmanga/api/catalogue.py
newmanga/api/manga.py
newmanga/api/popular.py
newmanga/api/read_now.py
newmanga/api/tags.py
newmanga/api/updates.py
newmanga/formatters/__init__.py
newmanga/formatters/json_to_object.py
newmanga/formatters/manga.py
newmanga/typing/__init__.py
newmanga/typing/enums.py
newmanga/typing/responses.py
newmanga/typing/types.py
newmanga-1.3.0.dist-info/METADATA
newmanga-1.3.0.dist-info/WHEEL
newmanga-1.3.0.dist-info/licenses/LICENSE
newmanga-1.3.0.dist-info/RECORD
