Metadata-Version: 2.3
Name: newmanga
Version: 1.3.0
Summary: This is not an official library written in python for getting manga from Newmanga website.
Project-URL: Homepage, https://github.com/progeroffline/newmanga
Project-URL: Issues, https://github.com/progeroffline/newmanga/issues
Author-email: Pavel Yatsenko <progeroffline@gmail.com>
License-File: LICENSE
Classifier: Intended Audience :: Developers
Classifier: License :: OSI Approved :: MIT License
Classifier: Operating System :: OS Independent
Classifier: Programming Language :: Python :: 3
Requires-Python: >=3.8
Requires-Dist: httpx
